wexa_sdk/__init__.py
wexa_sdk/agentflows.py
wexa_sdk/analytics.py
wexa_sdk/connectors_mgmt.py
wexa_sdk/executions.py
wexa_sdk/files.py
wexa_sdk/inbox.py
wexa_sdk/knowledgebase.py
wexa_sdk/llm.py
wexa_sdk/marketplace.py
wexa_sdk/projects.py
wexa_sdk/schedules.py
wexa_sdk/settings.py
wexa_sdk/skills.py
wexa_sdk/tables.py
wexa_sdk/tags.py
wexa_sdk/tasks.py
wexa_sdk/connectors/__init__.py
wexa_sdk/connectors/core.py
wexa_sdk/connectors/google_drive.py
wexa_sdk/core/__init__.py
wexa_sdk/core/http.py
wexa_sdk/models/__init__.py
wexa_sdk_public-0.1.0.dist-info/METADATA
wexa_sdk_public-0.1.0.dist-info/WHEEL
wexa_sdk_public-0.1.0.dist-info/top_level.txt
wexa_sdk_public-0.1.0.dist-info/RECORD
